flytekitplugins_perian_job_unofficial-1.13.13-py3.11-nspkg.pth
flytekitplugins/perian_job/__init__.py
flytekitplugins/perian_job/agent.py
flytekitplugins/perian_job/task.py
flytekitplugins_perian_job_unofficial-1.13.13.dist-info/METADATA
flytekitplugins_perian_job_unofficial-1.13.13.dist-info/WHEEL
flytekitplugins_perian_job_unofficial-1.13.13.dist-info/entry_points.txt
flytekitplugins_perian_job_unofficial-1.13.13.dist-info/namespace_packages.txt
flytekitplugins_perian_job_unofficial-1.13.13.dist-info/top_level.txt
flytekitplugins_perian_job_unofficial-1.13.13.dist-info/RECORD
