Metadata-Version: 2.1
Name: flytekitplugins-perian_job-unofficial
Version: 1.13.13
Summary: Flyte agent for Perian Job Platform (perian.io)
Author: Omar Tarabai
Author-email: otarabai@perian.io
License: apache2
Classifier: Intended Audience :: Science/Research
Classifier: Intended Audience :: Developers
Classifier: License :: OSI Approved :: Apache Software License
Classifier: Programming Language :: Python :: 3.8
Classifier: Programming Language :: Python :: 3.9
Classifier: Programming Language :: Python :: 3.10
Classifier: Programming Language :: Python :: 3.11
Classifier: Topic :: Scientific/Engineering
Classifier: Topic :: Scientific/Engineering :: Artificial Intelligence
Classifier: Topic :: Software Development
Classifier: Topic :: Software Development :: Libraries
Classifier: Topic :: Software Development :: Libraries :: Python Modules
Requires-Python: >=3.8
Requires-Dist: flytekit<2.0.0,>=1.12.0
Requires-Dist: perian>=0.2.7
